smartonnx/.DS_Store
smartonnx/__init__.py
smartonnx/entities/inputs.py
smartonnx/entities/operators.py
smartonnx/entities/tensors.py
smartonnx/main.py
smartonnx/templates/contract.cairo.tmpl
smartonnx/templates/tensor_loader.cairo.tmpl
smartonnx/utils.py
smartonnx-0.1.6.dist-info/METADATA
smartonnx-0.1.6.dist-info/WHEEL
smartonnx-0.1.6.dist-info/entry_points.txt
smartonnx-0.1.6.dist-info/RECORD
